{
  "Brands": "Brands",
  "InventoryManagement": "Inventory Management",
  "AddBrand": "Add Brand",
  "UpdateBrand": "Update Brand",
  "BrandName": "Brand Name",
  "SaveChanges": "Save Changes",
  "Close": "Close",
  "Today": "Today",
  "Devices": "Devices",
  "DeviceManagement": "Device Management",
  "DeviceSerialNumber": "Device Serial Number",
  "DeviceModel": "Device Model",
  "DevicePacketType": "Device Packet Type",
  "ConnectedVehicle": "Connected Vehicle",
  "Update": "Update",
  "Delete": "Delete",
  "UpdateDevice": "Update Device",
  "AddDevice": "Add Device",
  "PacketType": "Packet Type",
  "SerialNumber": "Serial Number",
  "Model": "Model",
  "Connected": "Connected",
  "NotConnected": "Not Connected",
  "Save": "Save",
  "DevicesRelatedToYourInventory": "Devices related to the products in your inventory",
  "Suppliers": "Suppliers",
  "DevicesConnectedToVehicle": "Devices Connected to Vehicle",
  "VehicleConnectedDeviceManagement": "Vehicle Connected Device Management",
  "VehiclePlate": "Vehicle Plate",
  "InstallationDateDeletionDate": "Installation Date / Deletion Date",
  "DisplaysDevicesConnectedToVehicles": "Displays devices connected to the vehicles in your inventory",
  "AddDeviceToVehicle": "Add Device to Vehicle",
  "UpdateVehicleDeviceConnection": "Update Vehicle Device Connection",
  "SerialNumberColon": "Serial Number:",
  "VehiclePlateColon": "Vehicle Plate:",
  "PageTitle": "Suppliers",
  "PageSubtitle": "Driver Management",
  "PageHeader": "Drivers",
  "InventoryDevices": "Devices related to the products in your inventory",
  "AddDriver": "Add Driver",
  "DriverName": "Driver Name",
  "DriverCode": "Driver Code",
  "UpdateDriver": "Update Driver",
  "Drivers": "Drivers",
  "DriverManagement": "Driver Management",
  "SelectedDate": "Selected Date",
  "DriversRelatedToYourInventory": "Drivers related to the products in your inventory",
  "AddMeasurementUnit": "Add Measurement Unit",
  "MeasurementUnitName": "Measurement Unit Name",
  "Models": "Models",
  "AddModel": "Add Model",
  "ModelName": "Model Name",
  "SelectBrand": "Select Brand",
  "UpdateModel": "Update Model",
  "ModelsRelatedToYourInventory": "Models related to the products in your inventory",
  "Packages": "Packages",
  "PackageManagement": "Package Management",
  "AddPackage": "Add Package",
  "UpdatePackage": "Update Package",
  "PackageDescription": "Package Description",
  "TodayColon": "Today:",
  "PackagesRelatedToYourInventory": "Packages associated with your inventory items",
  "PacketContents": "Packet Contents",
  "AddPacketContent": "Add Packet Content",
  "Description": "Description",
  "FieldName": "Field Name",
  "PacketName": "Packet Name",
  "DescriptionInformation": "Description Information",
  "UpdatePacketContent": "Update Packet Content",
  "VehicleMaintenance": "Vehicle Maintenance",
  "VehicleMaintenanceManagement": "Vehicle Maintenance Management",
  "VehicleMaintenanceInventory": "Maintenance of the vehicles in your inventory",
  "AddVehicleMaintenance": "Add Vehicle Maintenance",
  "LastMaintenanceDate": "Last Maintenance Date",
  "Period": "Period",
  "NextMaintenanceDate": "Next Maintenance Date",
  "DaysRemainingForMaintenance": "Days Remaining for Maintenance",
  "UpdateMaintenance": "Update Maintenance",
  "AddMaintenanceInformation": "Add Maintenance Information",
  "Vehicle": "Vehicle",
  "Add": "Add",
  "MaintenanceDay": "Maintenance Day!",
  "DaysPassed": "Days Passed",
  "DaysLeft": "Days Left",
  "Month": "Month",
  "UwingoVehicleTrackingSystemsManagement": "Uwingo Vehicle Tracking Systems Management",
  "TypeText": "Type text...",
  "Notifications": "Notifications",
  "YourOrderIsPlaced": "Your order is placed",
  "DummyTextOfPrintingAndIndustry": "Dummy text of the printing and industry.",
  "MeetingWithDesigners": "Meeting with designers",
  "UX3TaskComplete": "UX 3 Task complete.",
  "PaymentSuccessful": "Payment Successful",
  "ViewAll": "View all",
  "Profile": "Profile",
  "Settings": "Settings",
  "Logout": "Logout",
  "CreateNew": "Create New",
  "Dashboard": "Dashboard",
  "WelcomeToUwingo": "Welcome to Uwingo!",
  "AddSupplier": "Add Supplier",
  "UpdateSupplier": "Update Supplier",
  "SupplierName": "Supplier Name",
  "ContactInformation": "Contact Information",
  "SuppliersRelatedToYourInventory": "Suppliers of the products in your inventory",
  "Vehicles": "Vehicles",
  "VehicleManagement": "Vehicle Management",
  "ForRent": "For Rent",
  "Not": "Not",
  "Analytics": "Analytics",
  "Sessions": "Sessions",
  "AvgSessions": "Avg. Sessions",
  "BounceRate": "Bounce Rate",
  "GoalCompletions": "Goal Completions",
  "AudienceOverview": "Audience Overview",
  "SessionsDevice": "Sessions Device",
  "ThisYear": "This Year",
  "All": "All",
  "Purchases": "Purchases",
  "Emails": "Emails",
  "Desktops": "Desktops",
  "Tablets": "Tablets",
  "Mobiles": "Mobiles",
  "MapView": "Map View",
  "WholeWorldView": "Whole World View",
  "CountryView": "Country View",
  "CityView": "City View",
  "StreetView": "Street View",
  "AllVehicles": "All Vehicles",
  "Main": "Main",
  "Home": "Home",
  "Pages": "Pages",
  "DeviceConnectedVehicles": "Device Connected Vehicles",
  "DriverConnectedVehicle": "Driver Connected Vehicle",
  "VehicleMaintenancePeriod": "Vehicle Maintenance Period",
  "UwingoAcademy": "Uwingo Academy",
  "UwingoVehicleTrackingSystemManagementPanel": "Uwingo Vehicle Tracking System Management Panel",
  "LicensePlate": "License Plate",
  "Brand": "Brand",
  "Year": "Year",
  "ChassisNo": "Chassis No",
  "InitialKilometer": "Initial Kilometer",
  "IsThereADriver": "Is there a Driver?",
  "ForRentQuestion": "For Rent?",
  "Driver": "Driver",
  "AddedDateDeletedDate": "Added Date / Deleted Date",
  "AddVehicle": "Add Vehicle",
  "VehiclesRelatedToYourInventory": "Vehicles belonging to your products in your inventory",
  "VehicleBasedDriverManagement": "Vehicle-Based Driver Management",
  "VehicleConnectedDrivers": "Vehicle Connected Drivers",
  "DriversConnectedToVehiclesInYourInventory": "Drivers connected to your vehicles in your inventory",
  "AddDriverToVehicle": "Add Driver to Vehicle",
  "UpdateVehicleDriverLink": "Update Vehicle Driver Link",
  "NoAvailableVehiclesToChoose": "You have no available vehicles to choose from.",
  "NoDriversToChoose": "There are no drivers to choose from",
  "Yesterday": "Yesterday",
  "ThisWeek": "This Week",
  "Last30Days": "Last 30 Days",
  "ThisMonth": "This Month",
  "LastMonth": "Last Month",
  "Show": "Show",
  "DataRecordDate": "Data Record Date",
  "Latitude": "Latitude",
  "Longitude": "Longitude",
  "Speed": "Speed",
  "Altitude": "Altitude",
  "Odometer": "Odometer",
  "ContactStatus": "Contact Status",
  "FuelLevel": "Fuel Level",
  "NorthSouth": "North South",
  "EastWest": "East West",
  "Satellites": "Satellites",
  "COG": "COG",
  "InputPin1": "Input Pin 1",
  "InputPin2": "Input Pin 2",
  "OutputPin1": "Output Pin 1",
  "TotalFuelSpent": "Total Fuel Spent",
  "SignalStrength": "Signal Strength",
  "First": "First",
  "Previous": "Previous",
  "Next": "Next",
  "Active": "Active",
  "Last": "Last",
  "DeviceCount": "Device Count",
  "TotalDeviceCount": "Total Device Count",
  "TotalPackageCount": "Total Package Count",
  "NumberOfTrackedVehicles": "Number of Tracked Vehicles",
  "TotalTrackableVehicleCount": "Total Trackable Vehicle Count",
  "VehicleCount": "Vehicle Count",
  "TotalVehicleCount": "Total Vehicle Count",
  "VehicleTrackingData": "Vehicle Tracking Data",
  "ChassisNumber": "Chassis Number",
  "ModelYear": "Model Year",
  "IgnitionOn": "Ignition On",
  "IgnitionOff": "Ignition Off",
  "PinActive": "Pin Active",
  "PinInactive": "Pin Inactive",
  "NoRecordsToDisplay": "No records to display."
}